<Ui xmlns="http://www.blizzard.com/wow/ui/" xmlns:xsi="http://www.w3.org/2001/XMLSchema-instance">
  <Frame name="SS_ModifiersCreate_Menu" parent="SS_ModifiersControll_Menu" inherits = "SS_CloseableFrameWithBG_Template" hidden="true">
    <Scripts>
      <OnLoad>
        self:SetSize(430, 260);
        self.title:SetText('Создать модификатор');
        self.bg = "Interface\\AddOns\\SnowySystem\\IMG\\popup-background";
        self:RegisterForDrag("LeftButton");
        self.closeBtn:SetScript("OnClick", function()
          self:Hide();
          SS_ModifiersControll_Menu_Create_Button:SetText("+ Создать");
        end);
      </OnLoad>
    </Scripts>
    <Anchors>
      <Anchor point="TOPLEFT" x="0" y="270" relativeTo="SS_ModifiersControll_Menu" />
    </Anchors>
    <Layers>
      <Layer>
        <FontString font="Fonts\FRIZQT__.TTF" text="Идентификатор:">
          <Color r="1" g="1" b="1" a="1"/>
          <FontHeight val="12"/>
          <Anchors>
            <Anchor point="TOPLEFT" x="200" y="-45" />
          </Anchors>
        </FontString>
        <FontString font="Fonts\FRIZQT__.TTF" text="Имя:">
          <Color r="1" g="1" b="1" a="1"/>
          <FontHeight val="12"/>
          <Anchors>
            <Anchor point="TOPLEFT" x="200" y="-100" />
          </Anchors>
        </FontString>
        <FontString font="Fonts\FRIZQT__.TTF" text="Значение:">
          <Color r="1" g="1" b="1" a="1"/>
          <FontHeight val="12"/>
          <Anchors>
            <Anchor point="TOPLEFT" x="200" y="-155" />
          </Anchors>
        </FontString>
        <FontString font="Fonts\FRIZQT__.TTF" text="Бросков:">
          <Color r="1" g="1" b="1" a="1"/>
          <FontHeight val="12"/>
          <Anchors>
            <Anchor point="TOPLEFT" x="310" y="-155" />
          </Anchors>
        </FontString>
      </Layer>
    </Layers>
    <Frames>
      <ScrollFrame name="$parent_Scroll" inherits="UIPanelScrollFrameTemplate">
        <Anchors>
          <Anchor point="TOPLEFT" relativePoint="TOPLEFT" relativeTo="$parent" x="20" y="-45"/>
          <Anchor point="BOTTOMLEFT" relativePoint="BOTTOMLEFT" relativeTo="$parent" x="20" y="20"/>
          <Anchor point="RIGHT" relativePoint="TOPLEFT" relativeTo="$parent" x="160"/>
        </Anchors>
        <ScrollChild>
          <Frame name="$parent_Content">
            <Size>
              <AbsDimension x="180" y="1" />
            </Size>
            <Layers>
              <Layer>
                <FontString font="Fonts\FRIZQT__.TTF" text="Характеристики:">
                  <Color r="1" g="1" b="1" a="1"/>
                  <FontHeight val="12"/>
                  <Anchors>
                    <Anchor point="TOPLEFT" x="4" y="0" />
                  </Anchors>
                </FontString>
                <FontString font="Fonts\FRIZQT__.TTF" text="Навыки:">
                  <Color r="1" g="1" b="1" a="1"/>
                  <FontHeight val="12"/>
                  <Anchors>
                    <Anchor point="TOPLEFT" x="4" y="-210" />
                  </Anchors>
                </FontString>
              </Layer>
            </Layers>
            <Frames>
              <Frame parentKey = 'power' inherits="SS_CreateModifier_SelectCheckbox">
                <Scripts><OnLoad>self.stat = 'power'</OnLoad></Scripts>
                <Anchors>
                  <Anchor point="TOPLEFT">
                    <Offset><AbsDimension x="0" y="-25"></AbsDimension></Offset>
                  </Anchor>
                </Anchors>
              </Frame>
              <Frame parentKey = 'accuracy' inherits="SS_CreateModifier_SelectCheckbox">
                <Scripts><OnLoad>self.stat = 'accuracy'</OnLoad></Scripts>
                <Anchors>
                  <Anchor point="TOPLEFT">
                    <Offset><AbsDimension x="0" y="-50"></AbsDimension></Offset>
                  </Anchor>
                </Anchors>
              </Frame>
              <Frame parentKey = 'wisdom' inherits="SS_CreateModifier_SelectCheckbox">
                <Scripts><OnLoad>self.stat = 'wisdom'</OnLoad></Scripts>
                <Anchors>
                  <Anchor point="TOPLEFT">
                    <Offset><AbsDimension x="0" y="-75"></AbsDimension></Offset>
                  </Anchor>
                </Anchors>
              </Frame>
              <Frame parentKey = 'morale' inherits="SS_CreateModifier_SelectCheckbox">
                <Scripts><OnLoad>self.stat = 'morale'</OnLoad></Scripts>
                <Anchors>
                  <Anchor point="TOPLEFT">
                    <Offset><AbsDimension x="0" y="-100"></AbsDimension></Offset>
                  </Anchor>
                </Anchors>
              </Frame>
              <Frame parentKey = 'empathy' inherits="SS_CreateModifier_SelectCheckbox">
                <Scripts><OnLoad>self.stat = 'empathy'</OnLoad></Scripts>
                <Anchors>
                  <Anchor point="TOPLEFT">
                    <Offset><AbsDimension x="0" y="-125"></AbsDimension></Offset>
                  </Anchor>
                </Anchors>
              </Frame>
              <Frame parentKey = 'mobility' inherits="SS_CreateModifier_SelectCheckbox">
                <Scripts><OnLoad>self.stat = 'mobility'</OnLoad></Scripts>
                <Anchors>
                  <Anchor point="TOPLEFT">
                    <Offset><AbsDimension x="0" y="-150"></AbsDimension></Offset>
                  </Anchor>
                </Anchors>
              </Frame>
              <Frame parentKey = 'precision' inherits="SS_CreateModifier_SelectCheckbox">
                <Scripts><OnLoad>self.stat = 'precision'</OnLoad></Scripts>
                <Anchors>
                  <Anchor point="TOPLEFT">
                    <Offset><AbsDimension x="0" y="-175"></AbsDimension></Offset>
                  </Anchor>
                </Anchors>
              </Frame>
              <Frame parentKey = 'melee' inherits="SS_CreateModifier_SelectCheckbox">
                <Scripts><OnLoad>self.stat = 'melee'</OnLoad></Scripts>
                <Anchors>
                  <Anchor point="TOPLEFT">
                    <Offset><AbsDimension x="0" y="-235"></AbsDimension></Offset>
                  </Anchor>
                </Anchors>
              </Frame>
              <Frame parentKey = 'range' inherits="SS_CreateModifier_SelectCheckbox">
                <Scripts><OnLoad>self.stat = 'range'</OnLoad></Scripts>
                <Anchors>
                  <Anchor point="TOPLEFT">
                    <Offset><AbsDimension x="0" y="-260"></AbsDimension></Offset>
                  </Anchor>
                </Anchors>
              </Frame>
              <Frame parentKey = 'magic' inherits="SS_CreateModifier_SelectCheckbox">
                <Scripts><OnLoad>self.stat = 'magic'</OnLoad></Scripts>
                <Anchors>
                  <Anchor point="TOPLEFT">
                    <Offset><AbsDimension x="0" y="-285"></AbsDimension></Offset>
                  </Anchor>
                </Anchors>
              </Frame>
              <Frame parentKey = 'religion' inherits="SS_CreateModifier_SelectCheckbox">
                <Scripts><OnLoad>self.stat = 'religion'</OnLoad></Scripts>
                <Anchors>
                  <Anchor point="TOPLEFT">
                    <Offset><AbsDimension x="0" y="-310"></AbsDimension></Offset>
                  </Anchor>
                </Anchors>
              </Frame>
              <Frame parentKey = 'perfomance' inherits="SS_CreateModifier_SelectCheckbox">
                <Scripts><OnLoad>self.stat = 'perfomance'</OnLoad></Scripts>
                <Anchors>
                  <Anchor point="TOPLEFT">
                    <Offset><AbsDimension x="0" y="-335"></AbsDimension></Offset>
                  </Anchor>
                </Anchors>
              </Frame>
              <Frame parentKey = 'missing' inherits="SS_CreateModifier_SelectCheckbox">
                <Scripts><OnLoad>self.stat = 'missing'</OnLoad></Scripts>
                <Anchors>
                  <Anchor point="TOPLEFT">
                    <Offset><AbsDimension x="0" y="-360"></AbsDimension></Offset>
                  </Anchor>
                </Anchors>
              </Frame>
              <Frame parentKey = 'hands' inherits="SS_CreateModifier_SelectCheckbox">
                <Scripts><OnLoad>self.stat = 'hands'</OnLoad></Scripts>
                <Anchors>
                  <Anchor point="TOPLEFT">
                    <Offset><AbsDimension x="0" y="-385"></AbsDimension></Offset>
                  </Anchor>
                </Anchors>
              </Frame>
              <Frame parentKey = 'athletics' inherits="SS_CreateModifier_SelectCheckbox">
                <Scripts><OnLoad>self.stat = 'athletics'</OnLoad></Scripts>
                <Anchors>
                  <Anchor point="TOPLEFT">
                    <Offset><AbsDimension x="0" y="-410"></AbsDimension></Offset>
                  </Anchor>
                </Anchors>
              </Frame>
              <Frame parentKey = 'observation' inherits="SS_CreateModifier_SelectCheckbox">
                <Scripts><OnLoad>self.stat = 'observation'</OnLoad></Scripts>
                <Anchors>
                  <Anchor point="TOPLEFT">
                    <Offset><AbsDimension x="0" y="-435"></AbsDimension></Offset>
                  </Anchor>
                </Anchors>
              </Frame>
              <Frame parentKey = 'knowledge' inherits="SS_CreateModifier_SelectCheckbox">
                <Scripts><OnLoad>self.stat = 'knowledge'</OnLoad></Scripts>
                <Anchors>
                  <Anchor point="TOPLEFT">
                    <Offset><AbsDimension x="0" y="-460"></AbsDimension></Offset>
                  </Anchor>
                </Anchors>
              </Frame>
              <Frame parentKey = 'controll' inherits="SS_CreateModifier_SelectCheckbox">
                <Scripts><OnLoad>self.stat = 'controll'</OnLoad></Scripts>
                <Anchors>
                  <Anchor point="TOPLEFT">
                    <Offset><AbsDimension x="0" y="-485"></AbsDimension></Offset>
                  </Anchor>
                </Anchors>
              </Frame>
              <Frame parentKey = 'judgment' inherits="SS_CreateModifier_SelectCheckbox">
                <Scripts><OnLoad>self.stat = 'judgment'</OnLoad></Scripts>
                <Anchors>
                  <Anchor point="TOPLEFT">
                    <Offset><AbsDimension x="0" y="-510"></AbsDimension></Offset>
                  </Anchor>
                </Anchors>
              </Frame>
              <Frame parentKey = 'acrobats' inherits="SS_CreateModifier_SelectCheckbox">
                <Scripts><OnLoad>self.stat = 'acrobats'</OnLoad></Scripts>
                <Anchors>
                  <Anchor point="TOPLEFT">
                    <Offset><AbsDimension x="0" y="-535"></AbsDimension></Offset>
                  </Anchor>
                </Anchors>
              </Frame>
              <Frame parentKey = 'stealth' inherits="SS_CreateModifier_SelectCheckbox">
                <Scripts><OnLoad>self.stat = 'stealth'</OnLoad></Scripts>
                <Anchors>
                  <Anchor point="TOPLEFT">
                    <Offset><AbsDimension x="0" y="-560"></AbsDimension></Offset>
                  </Anchor>
                </Anchors>
              </Frame>
            </Frames>
          </Frame>
        </ScrollChild>
      </ScrollFrame>
      <EditBox parentKey = "id" inherits="SS_Form_EditBox">
        <Scripts>
          <OnEscapePressed>
            self:ClearFocus();
          </OnEscapePressed>
          <OnTabPressed>
            SS_ModifiersCreate_Menu.name:SetFocus();
          </OnTabPressed>
        </Scripts>
        <Anchors>
          <Anchor point="TOPLEFT">
            <Offset><AbsDimension x="200" y="-65"/></Offset>
          </Anchor>
        </Anchors>
      </EditBox>
      <EditBox parentKey = "name" inherits="SS_Form_EditBox">
        <Scripts>
          <OnEscapePressed>
            self:ClearFocus();
          </OnEscapePressed>
          <OnTabPressed>
            SS_ModifiersCreate_Menu.value:SetFocus();
          </OnTabPressed>
        </Scripts>
        <Anchors>
          <Anchor point="TOPLEFT">
            <Offset><AbsDimension x="200" y="-120"/></Offset>
          </Anchor>
        </Anchors>
      </EditBox>
      <EditBox parentKey = "value" inherits="SS_Form_EditBox">
        <Scripts>
          <OnShow>
            self:SetNumeric();
          </OnShow>
          <OnEscapePressed>
            self:ClearFocus();
          </OnEscapePressed>
          <OnTabPressed>
            SS_ModifiersCreate_Menu.count:SetFocus();
          </OnTabPressed>
        </Scripts>
        <Size x="90" y="26" />
        <Anchors>
          <Anchor point="TOPLEFT">
            <Offset><AbsDimension x="200" y="-175"/></Offset>
          </Anchor>
        </Anchors>
      </EditBox>
      <EditBox parentKey = "count" inherits="SS_Form_EditBox">
        <Scripts>
          <OnShow>
            self:SetNumeric();
          </OnShow>
          <OnEscapePressed>
            self:ClearFocus();
          </OnEscapePressed>
          <OnTabPressed>
            SS_ModifiersCreate_Menu.id:SetFocus();
          </OnTabPressed>
        </Scripts>
        <Size x="90" y="26" />
        <Anchors>
          <Anchor point="TOPLEFT">
            <Offset><AbsDimension x="310" y="-175"/></Offset>
          </Anchor>
        </Anchors>
      </EditBox>
      <Button name="$parent_Submit_Button" inherits="OptionsButtonTemplate" text="Создать">
        <Size x = "80" y = "26" />
        <Anchors>
          <Anchor point="BOTTOMRIGHT">
            <Offset x="-20" y="20"/>
          </Anchor> 
        </Anchors>
        <Scripts>
          <OnClick>
            SS_ModifierCreate_Create();
          </OnClick>
        </Scripts>
      </Button>
    </Frames>
  </Frame>
</Ui>

